{
    "Version": "1.2",
    "Data": {
        "Source": "c:\\users\\oli\\documents\\github\\abot-master\\1.0\\src\\dllmain.cpp",
        "ProvidedModule": "",
        "Includes": [
            "c:\\program files (x86)\\windows kits\\10\\include\\10.0.22621.0\\um\\windows.h",
            "c:\\program files (x86)\\windows kits\\10\\include\\10.0.22621.0\\shared\\winapifamily.h",
            "c:\\program files (x86)\\windows kits\\10\\include\\10.0.22621.0\\shared\\winpackagefamily.h",
            "c:\\program files (x86)\\windows kits\\10\\include\\10.0.22621.0\\shared\\sdkddkver.h",
            "c:\\program files\\microsoft visual studio\\2022\\community\\vc\\tools\\msvc\\14.43.34808\\include\\excpt.h",
            "c:\\program files\\microsoft visual studio\\2022\\community\\vc\\tools\\msvc\\14.43.34808\\include\\vcruntime.h",
            "c:\\program files\\microsoft visual studio\\2022\\community\\vc\\tools\\msvc\\14.43.34808\\include\\sal.h",
            "c:\\program files\\microsoft visual studio\\2022\\community\\vc\\tools\\msvc\\14.43.34808\\include\\concurrencysal.h",
            "c:\\program files\\microsoft visual studio\\2022\\community\\vc\\tools\\msvc\\14.43.34808\\include\\vadefs.h",
            "c:\\program files\\microsoft visual studio\\2022\\community\\vc\\tools\\msvc\\14.43.34808\\include\\stdarg.h",
            "c:\\program files (x86)\\windows kits\\10\\include\\10.0.22621.0\\shared\\windef.h",
            "c:\\program files (x86)\\windows kits\\10\\include\\10.0.22621.0\\shared\\minwindef.h",
            "c:\\program files (x86)\\windows kits\\10\\include\\10.0.22621.0\\shared\\specstrings.h",
            "c:\\program files (x86)\\windows kits\\10\\include\\10.0.22621.0\\shared\\specstrings_strict.h",
            "c:\\program files (x86)\\windows kits\\10\\include\\10.0.22621.0\\shared\\specstrings_undef.h",
            "c:\\program files (x86)\\windows kits\\10\\include\\10.0.22621.0\\shared\\driverspecs.h",
            "c:\\program files (x86)\\windows kits\\10\\include\\10.0.22621.0\\shared\\sdv_driverspecs.h",
            "c:\\program files (x86)\\windows kits\\10\\include\\10.0.22621.0\\um\\winnt.h",
            "c:\\program files (x86)\\windows kits\\10\\include\\10.0.22621.0\\ucrt\\ctype.h",
            "c:\\program files (x86)\\windows kits\\10\\include\\10.0.22621.0\\ucrt\\corecrt.h",
            "c:\\program files (x86)\\windows kits\\10\\include\\10.0.22621.0\\ucrt\\corecrt_wctype.h",
            "c:\\program files (x86)\\windows kits\\10\\include\\10.0.22621.0\\shared\\kernelspecs.h",
            "c:\\program files (x86)\\windows kits\\10\\include\\10.0.22621.0\\shared\\basetsd.h",
            "c:\\program files (x86)\\windows kits\\10\\include\\10.0.22621.0\\shared\\guiddef.h",
            "c:\\program files (x86)\\windows kits\\10\\include\\10.0.22621.0\\ucrt\\string.h",
            "c:\\program files (x86)\\windows kits\\10\\include\\10.0.22621.0\\ucrt\\corecrt_memory.h",
            "c:\\program files (x86)\\windows kits\\10\\include\\10.0.22621.0\\ucrt\\corecrt_memcpy_s.h",
            "c:\\program files (x86)\\windows kits\\10\\include\\10.0.22621.0\\ucrt\\errno.h",
            "c:\\program files\\microsoft visual studio\\2022\\community\\vc\\tools\\msvc\\14.43.34808\\include\\vcruntime_string.h",
            "c:\\program files (x86)\\windows kits\\10\\include\\10.0.22621.0\\ucrt\\corecrt_wstring.h",
            "c:\\program files (x86)\\windows kits\\10\\include\\10.0.22621.0\\shared\\pshpack4.h",
            "c:\\program files (x86)\\windows kits\\10\\include\\10.0.22621.0\\shared\\poppack.h",
            "c:\\program files (x86)\\windows kits\\10\\include\\10.0.22621.0\\shared\\pshpack4.h",
            "c:\\program files (x86)\\windows kits\\10\\include\\10.0.22621.0\\shared\\poppack.h",
            "c:\\program files (x86)\\windows kits\\10\\include\\10.0.22621.0\\shared\\pshpack4.h",
            "c:\\program files (x86)\\windows kits\\10\\include\\10.0.22621.0\\shared\\poppack.h",
            "c:\\program files (x86)\\windows kits\\10\\include\\10.0.22621.0\\shared\\pshpack4.h",
            "c:\\program files (x86)\\windows kits\\10\\include\\10.0.22621.0\\shared\\pshpack2.h",
            "c:\\program files (x86)\\windows kits\\10\\include\\10.0.22621.0\\shared\\poppack.h",
            "c:\\program files (x86)\\windows kits\\10\\include\\10.0.22621.0\\shared\\pshpack2.h",
            "c:\\program files (x86)\\windows kits\\10\\include\\10.0.22621.0\\shared\\pshpack2.h",
            "c:\\program files (x86)\\windows kits\\10\\include\\10.0.22621.0\\shared\\poppack.h",
            "c:\\program files (x86)\\windows kits\\10\\include\\10.0.22621.0\\shared\\poppack.h",
            "c:\\program files (x86)\\windows kits\\10\\include\\10.0.22621.0\\shared\\pshpack8.h",
            "c:\\program files (x86)\\windows kits\\10\\include\\10.0.22621.0\\shared\\poppack.h",
            "c:\\program files (x86)\\windows kits\\10\\include\\10.0.22621.0\\shared\\pshpack1.h",
            "c:\\program files (x86)\\windows kits\\10\\include\\10.0.22621.0\\shared\\poppack.h",
            "c:\\program files (x86)\\windows kits\\10\\include\\10.0.22621.0\\shared\\pshpack1.h",
            "c:\\program files (x86)\\windows kits\\10\\include\\10.0.22621.0\\shared\\poppack.h",
            "c:\\program files (x86)\\windows kits\\10\\include\\10.0.22621.0\\shared\\poppack.h",
            "c:\\program files (x86)\\windows kits\\10\\include\\10.0.22621.0\\shared\\apiset.h",
            "c:\\program files (x86)\\windows kits\\10\\include\\10.0.22621.0\\shared\\ktmtypes.h",
            "c:\\program files (x86)\\windows kits\\10\\include\\10.0.22621.0\\um\\winbase.h",
            "c:\\program files (x86)\\windows kits\\10\\include\\10.0.22621.0\\shared\\apisetcconv.h",
            "c:\\program files (x86)\\windows kits\\10\\include\\10.0.22621.0\\um\\minwinbase.h",
            "c:\\program files (x86)\\windows kits\\10\\include\\10.0.22621.0\\um\\apiquery2.h",
            "c:\\program files (x86)\\windows kits\\10\\include\\10.0.22621.0\\um\\processenv.h",
            "c:\\program files (x86)\\windows kits\\10\\include\\10.0.22621.0\\um\\fileapifromapp.h",
            "c:\\program files (x86)\\windows kits\\10\\include\\10.0.22621.0\\um\\fileapi.h",
            "c:\\program files (x86)\\windows kits\\10\\include\\10.0.22621.0\\um\\debugapi.h",
            "c:\\program files (x86)\\windows kits\\10\\include\\10.0.22621.0\\um\\utilapiset.h",
            "c:\\program files (x86)\\windows kits\\10\\include\\10.0.22621.0\\um\\handleapi.h",
            "c:\\program files (x86)\\windows kits\\10\\include\\10.0.22621.0\\um\\errhandlingapi.h",
            "c:\\program files (x86)\\windows kits\\10\\include\\10.0.22621.0\\um\\fibersapi.h",
            "c:\\program files (x86)\\windows kits\\10\\include\\10.0.22621.0\\um\\namedpipeapi.h",
            "c:\\program files (x86)\\windows kits\\10\\include\\10.0.22621.0\\um\\profileapi.h",
            "c:\\program files (x86)\\windows kits\\10\\include\\10.0.22621.0\\um\\heapapi.h",
            "c:\\program files (x86)\\windows kits\\10\\include\\10.0.22621.0\\um\\ioapiset.h",
            "c:\\program files (x86)\\windows kits\\10\\include\\10.0.22621.0\\um\\synchapi.h",
            "c:\\program files (x86)\\windows kits\\10\\include\\10.0.22621.0\\um\\interlockedapi.h",
            "c:\\program files (x86)\\windows kits\\10\\include\\10.0.22621.0\\um\\processthreadsapi.h",
            "c:\\program files (x86)\\windows kits\\10\\include\\10.0.22621.0\\um\\sysinfoapi.h",
            "c:\\program files (x86)\\windows kits\\10\\include\\10.0.22621.0\\um\\memoryapi.h",
            "c:\\program files (x86)\\windows kits\\10\\include\\10.0.22621.0\\um\\enclaveapi.h",
            "c:\\program files (x86)\\windows kits\\10\\include\\10.0.22621.0\\um\\threadpoollegacyapiset.h",
            "c:\\program files (x86)\\windows kits\\10\\include\\10.0.22621.0\\um\\threadpoolapiset.h",
            "c:\\program files (x86)\\windows kits\\10\\include\\10.0.22621.0\\um\\jobapi.h",
            "c:\\program files (x86)\\windows kits\\10\\include\\10.0.22621.0\\um\\jobapi2.h",
            "c:\\program files (x86)\\windows kits\\10\\include\\10.0.22621.0\\um\\wow64apiset.h",
            "c:\\program files (x86)\\windows kits\\10\\include\\10.0.22621.0\\um\\libloaderapi.h",
            "c:\\program files (x86)\\windows kits\\10\\include\\10.0.22621.0\\um\\securitybaseapi.h",
            "c:\\program files (x86)\\windows kits\\10\\include\\10.0.22621.0\\um\\namespaceapi.h",
            "c:\\program files (x86)\\windows kits\\10\\include\\10.0.22621.0\\um\\systemtopologyapi.h",
            "c:\\program files (x86)\\windows kits\\10\\include\\10.0.22621.0\\um\\processtopologyapi.h",
            "c:\\program files (x86)\\windows kits\\10\\include\\10.0.22621.0\\um\\securityappcontainer.h",
            "c:\\program files (x86)\\windows kits\\10\\include\\10.0.22621.0\\um\\realtimeapiset.h",
            "c:\\program files (x86)\\windows kits\\10\\include\\10.0.22621.0\\shared\\winerror.h",
            "c:\\program files (x86)\\windows kits\\10\\include\\10.0.22621.0\\um\\timezoneapi.h",
            "c:\\program files (x86)\\windows kits\\10\\include\\10.0.22621.0\\um\\wingdi.h",
            "c:\\program files (x86)\\windows kits\\10\\include\\10.0.22621.0\\shared\\pshpack1.h",
            "c:\\program files (x86)\\windows kits\\10\\include\\10.0.22621.0\\shared\\poppack.h",
            "c:\\program files (x86)\\windows kits\\10\\include\\10.0.22621.0\\shared\\pshpack2.h",
            "c:\\program files (x86)\\windows kits\\10\\include\\10.0.22621.0\\shared\\poppack.h",
            "c:\\program files (x86)\\windows kits\\10\\include\\10.0.22621.0\\shared\\pshpack2.h",
            "c:\\program files (x86)\\windows kits\\10\\include\\10.0.22621.0\\shared\\poppack.h",
            "c:\\program files (x86)\\windows kits\\10\\include\\10.0.22621.0\\shared\\pshpack4.h",
            "c:\\program files (x86)\\windows kits\\10\\include\\10.0.22621.0\\shared\\poppack.h",
            "c:\\program files (x86)\\windows kits\\10\\include\\10.0.22621.0\\shared\\pshpack4.h",
            "c:\\program files (x86)\\windows kits\\10\\include\\10.0.22621.0\\shared\\poppack.h",
            "c:\\program files (x86)\\windows kits\\10\\include\\10.0.22621.0\\um\\winuser.h",
            "c:\\program files (x86)\\windows kits\\10\\include\\10.0.22621.0\\shared\\pshpack2.h",
            "c:\\program files (x86)\\windows kits\\10\\include\\10.0.22621.0\\shared\\poppack.h",
            "c:\\program files (x86)\\windows kits\\10\\include\\10.0.22621.0\\shared\\tvout.h",
            "c:\\program files (x86)\\windows kits\\10\\include\\10.0.22621.0\\um\\winnls.h",
            "c:\\program files (x86)\\windows kits\\10\\include\\10.0.22621.0\\um\\datetimeapi.h",
            "c:\\program files (x86)\\windows kits\\10\\include\\10.0.22621.0\\um\\stringapiset.h",
            "c:\\program files (x86)\\windows kits\\10\\include\\10.0.22621.0\\um\\winnls.h",
            "c:\\program files (x86)\\windows kits\\10\\include\\10.0.22621.0\\um\\wincon.h",
            "c:\\program files (x86)\\windows kits\\10\\include\\10.0.22621.0\\um\\wincontypes.h",
            "c:\\program files (x86)\\windows kits\\10\\include\\10.0.22621.0\\um\\consoleapi.h",
            "c:\\program files (x86)\\windows kits\\10\\include\\10.0.22621.0\\um\\consoleapi2.h",
            "c:\\program files (x86)\\windows kits\\10\\include\\10.0.22621.0\\um\\consoleapi3.h",
            "c:\\program files (x86)\\windows kits\\10\\include\\10.0.22621.0\\um\\winver.h",
            "c:\\program files (x86)\\windows kits\\10\\include\\10.0.22621.0\\um\\verrsrc.h",
            "c:\\program files (x86)\\windows kits\\10\\include\\10.0.22621.0\\um\\winreg.h",
            "c:\\program files (x86)\\windows kits\\10\\include\\10.0.22621.0\\um\\reason.h",
            "c:\\program files (x86)\\windows kits\\10\\include\\10.0.22621.0\\um\\winnetwk.h",
            "c:\\program files (x86)\\windows kits\\10\\include\\10.0.22621.0\\shared\\wnnc.h",
            "c:\\program files (x86)\\windows kits\\10\\include\\10.0.22621.0\\shared\\cderr.h",
            "c:\\program files (x86)\\windows kits\\10\\include\\10.0.22621.0\\um\\dde.h",
            "c:\\program files (x86)\\windows kits\\10\\include\\10.0.22621.0\\um\\ddeml.h",
            "c:\\program files (x86)\\windows kits\\10\\include\\10.0.22621.0\\um\\dlgs.h",
            "c:\\program files (x86)\\windows kits\\10\\include\\10.0.22621.0\\um\\lzexpand.h",
            "c:\\program files (x86)\\windows kits\\10\\include\\10.0.22621.0\\um\\mmsystem.h",
            "c:\\program files (x86)\\windows kits\\10\\include\\10.0.22621.0\\um\\mmsyscom.h",
            "c:\\program files (x86)\\windows kits\\10\\include\\10.0.22621.0\\shared\\pshpack1.h",
            "c:\\program files (x86)\\windows kits\\10\\include\\10.0.22621.0\\shared\\poppack.h",
            "c:\\program files (x86)\\windows kits\\10\\include\\10.0.22621.0\\shared\\pshpack1.h",
            "c:\\program files (x86)\\windows kits\\10\\include\\10.0.22621.0\\um\\mciapi.h",
            "c:\\program files (x86)\\windows kits\\10\\include\\10.0.22621.0\\um\\mmsyscom.h",
            "c:\\program files (x86)\\windows kits\\10\\include\\10.0.22621.0\\um\\mmiscapi.h",
            "c:\\program files (x86)\\windows kits\\10\\include\\10.0.22621.0\\um\\mmsyscom.h",
            "c:\\program files (x86)\\windows kits\\10\\include\\10.0.22621.0\\um\\mmiscapi2.h",
            "c:\\program files (x86)\\windows kits\\10\\include\\10.0.22621.0\\um\\mmsyscom.h",
            "c:\\program files (x86)\\windows kits\\10\\include\\10.0.22621.0\\um\\playsoundapi.h",
            "c:\\program files (x86)\\windows kits\\10\\include\\10.0.22621.0\\um\\mmsyscom.h",
            "c:\\program files (x86)\\windows kits\\10\\include\\10.0.22621.0\\um\\mmeapi.h",
            "c:\\program files (x86)\\windows kits\\10\\include\\10.0.22621.0\\um\\mmsyscom.h",
            "c:\\program files (x86)\\windows kits\\10\\include\\10.0.22621.0\\um\\timeapi.h",
            "c:\\program files (x86)\\windows kits\\10\\include\\10.0.22621.0\\um\\mmsyscom.h",
            "c:\\program files (x86)\\windows kits\\10\\include\\10.0.22621.0\\um\\joystickapi.h",
            "c:\\program files (x86)\\windows kits\\10\\include\\10.0.22621.0\\um\\mmsyscom.h",
            "c:\\program files (x86)\\windows kits\\10\\include\\10.0.22621.0\\shared\\poppack.h",
            "c:\\program files (x86)\\windows kits\\10\\include\\10.0.22621.0\\um\\nb30.h",
            "c:\\program files (x86)\\windows kits\\10\\include\\10.0.22621.0\\shared\\rpc.h",
            "c:\\program files (x86)\\windows kits\\10\\include\\10.0.22621.0\\shared\\rpcdce.h",
            "c:\\program files (x86)\\windows kits\\10\\include\\10.0.22621.0\\shared\\rpcdcep.h",
            "c:\\program files (x86)\\windows kits\\10\\include\\10.0.22621.0\\um\\rpcnsi.h",
            "c:\\program files (x86)\\windows kits\\10\\include\\10.0.22621.0\\shared\\rpcnterr.h",
            "c:\\program files (x86)\\windows kits\\10\\include\\10.0.22621.0\\shared\\rpcasync.h",
            "c:\\program files (x86)\\windows kits\\10\\include\\10.0.22621.0\\um\\shellapi.h",
            "c:\\program files (x86)\\windows kits\\10\\include\\10.0.22621.0\\shared\\pshpack1.h",
            "c:\\program files (x86)\\windows kits\\10\\include\\10.0.22621.0\\shared\\poppack.h",
            "c:\\program files (x86)\\windows kits\\10\\include\\10.0.22621.0\\um\\winperf.h",
            "c:\\program files (x86)\\windows kits\\10\\include\\10.0.22621.0\\shared\\pshpack8.h",
            "c:\\program files (x86)\\windows kits\\10\\include\\10.0.22621.0\\shared\\poppack.h",
            "c:\\program files (x86)\\windows kits\\10\\include\\10.0.22621.0\\um\\winsock.h",
            "c:\\program files (x86)\\windows kits\\10\\include\\10.0.22621.0\\shared\\inaddr.h",
            "c:\\program files (x86)\\windows kits\\10\\include\\10.0.22621.0\\um\\wincrypt.h",
            "c:\\program files (x86)\\windows kits\\10\\include\\10.0.22621.0\\shared\\bcrypt.h",
            "c:\\program files (x86)\\windows kits\\10\\include\\10.0.22621.0\\um\\ncrypt.h",
            "c:\\program files (x86)\\windows kits\\10\\include\\10.0.22621.0\\um\\dpapi.h",
            "c:\\program files (x86)\\windows kits\\10\\include\\10.0.22621.0\\um\\winefs.h",
            "c:\\program files (x86)\\windows kits\\10\\include\\10.0.22621.0\\um\\winscard.h",
            "c:\\program files (x86)\\windows kits\\10\\include\\10.0.22621.0\\shared\\wtypes.h",
            "c:\\program files (x86)\\windows kits\\10\\include\\10.0.22621.0\\shared\\rpcndr.h",
            "c:\\program files (x86)\\windows kits\\10\\include\\10.0.22621.0\\shared\\pshpack8.h",
            "c:\\program files (x86)\\windows kits\\10\\include\\10.0.22621.0\\um\\rpcnsip.h",
            "c:\\program files (x86)\\windows kits\\10\\include\\10.0.22621.0\\shared\\rpcsal.h",
            "c:\\program files (x86)\\windows kits\\10\\include\\10.0.22621.0\\shared\\poppack.h",
            "c:\\program files (x86)\\windows kits\\10\\include\\10.0.22621.0\\shared\\wtypesbase.h",
            "c:\\program files (x86)\\windows kits\\10\\include\\10.0.22621.0\\shared\\guiddef.h",
            "c:\\program files (x86)\\windows kits\\10\\include\\10.0.22621.0\\um\\winioctl.h",
            "c:\\program files (x86)\\windows kits\\10\\include\\10.0.22621.0\\shared\\pshpack1.h",
            "c:\\program files (x86)\\windows kits\\10\\include\\10.0.22621.0\\shared\\poppack.h",
            "c:\\program files (x86)\\windows kits\\10\\include\\10.0.22621.0\\shared\\pshpack1.h",
            "c:\\program files (x86)\\windows kits\\10\\include\\10.0.22621.0\\shared\\poppack.h",
            "c:\\program files (x86)\\windows kits\\10\\include\\10.0.22621.0\\shared\\pshpack1.h",
            "c:\\program files (x86)\\windows kits\\10\\include\\10.0.22621.0\\shared\\poppack.h",
            "c:\\program files (x86)\\windows kits\\10\\include\\10.0.22621.0\\shared\\pshpack1.h",
            "c:\\program files (x86)\\windows kits\\10\\include\\10.0.22621.0\\shared\\poppack.h",
            "c:\\program files (x86)\\windows kits\\10\\include\\10.0.22621.0\\shared\\pshpack1.h",
            "c:\\program files (x86)\\windows kits\\10\\include\\10.0.22621.0\\shared\\poppack.h",
            "c:\\program files (x86)\\windows kits\\10\\include\\10.0.22621.0\\shared\\pshpack1.h",
            "c:\\program files (x86)\\windows kits\\10\\include\\10.0.22621.0\\shared\\poppack.h",
            "c:\\program files (x86)\\windows kits\\10\\include\\10.0.22621.0\\shared\\pshpack1.h",
            "c:\\program files (x86)\\windows kits\\10\\include\\10.0.22621.0\\shared\\poppack.h",
            "c:\\program files (x86)\\windows kits\\10\\include\\10.0.22621.0\\shared\\winsmcrd.h",
            "c:\\program files (x86)\\windows kits\\10\\include\\10.0.22621.0\\um\\winspool.h",
            "c:\\program files (x86)\\windows kits\\10\\include\\10.0.22621.0\\um\\prsht.h",
            "c:\\program files (x86)\\windows kits\\10\\include\\10.0.22621.0\\shared\\pshpack4.h",
            "c:\\program files (x86)\\windows kits\\10\\include\\10.0.22621.0\\shared\\poppack.h",
            "c:\\program files (x86)\\windows kits\\10\\include\\10.0.22621.0\\um\\ole2.h",
            "c:\\program files (x86)\\windows kits\\10\\include\\10.0.22621.0\\shared\\pshpack8.h",
            "c:\\program files (x86)\\windows kits\\10\\include\\10.0.22621.0\\um\\objbase.h",
            "c:\\program files (x86)\\windows kits\\10\\include\\10.0.22621.0\\shared\\pshpack8.h",
            "c:\\program files (x86)\\windows kits\\10\\include\\10.0.22621.0\\um\\combaseapi.h",
            "c:\\program files (x86)\\windows kits\\10\\include\\10.0.22621.0\\shared\\pshpack8.h",
            "c:\\program files (x86)\\windows kits\\10\\include\\10.0.22621.0\\ucrt\\stdlib.h",
            "c:\\program files (x86)\\windows kits\\10\\include\\10.0.22621.0\\ucrt\\corecrt_malloc.h",
            "c:\\program files (x86)\\windows kits\\10\\include\\10.0.22621.0\\ucrt\\corecrt_search.h",
            "c:\\program files (x86)\\windows kits\\10\\include\\10.0.22621.0\\ucrt\\stddef.h",
            "c:\\program files (x86)\\windows kits\\10\\include\\10.0.22621.0\\ucrt\\corecrt_wstdlib.h",
            "c:\\program files\\microsoft visual studio\\2022\\community\\vc\\tools\\msvc\\14.43.34808\\include\\limits.h",
            "c:\\program files (x86)\\windows kits\\10\\include\\10.0.22621.0\\um\\unknwnbase.h",
            "c:\\program files (x86)\\windows kits\\10\\include\\10.0.22621.0\\um\\objidlbase.h",
            "c:\\program files (x86)\\windows kits\\10\\include\\10.0.22621.0\\shared\\guiddef.h",
            "c:\\program files (x86)\\windows kits\\10\\include\\10.0.22621.0\\um\\cguid.h",
            "c:\\program files (x86)\\windows kits\\10\\include\\10.0.22621.0\\shared\\poppack.h",
            "c:\\program files (x86)\\windows kits\\10\\include\\10.0.22621.0\\um\\coml2api.h",
            "c:\\program files (x86)\\windows kits\\10\\include\\10.0.22621.0\\um\\objidl.h",
            "c:\\program files (x86)\\windows kits\\10\\include\\10.0.22621.0\\um\\unknwn.h",
            "c:\\program files (x86)\\windows kits\\10\\include\\10.0.22621.0\\um\\propidlbase.h",
            "c:\\program files (x86)\\windows kits\\10\\include\\10.0.22621.0\\um\\oaidl.h",
            "c:\\program files (x86)\\windows kits\\10\\include\\10.0.22621.0\\um\\urlmon.h",
            "c:\\program files (x86)\\windows kits\\10\\include\\10.0.22621.0\\um\\oleidl.h",
            "c:\\program files (x86)\\windows kits\\10\\include\\10.0.22621.0\\um\\servprov.h",
            "c:\\program files (x86)\\windows kits\\10\\include\\10.0.22621.0\\um\\msxml.h",
            "c:\\program files (x86)\\windows kits\\10\\include\\10.0.22621.0\\um\\propidl.h",
            "c:\\program files (x86)\\windows kits\\10\\include\\10.0.22621.0\\shared\\poppack.h",
            "c:\\program files (x86)\\windows kits\\10\\include\\10.0.22621.0\\um\\oleauto.h",
            "c:\\program files (x86)\\windows kits\\10\\include\\10.0.22621.0\\shared\\pshpack8.h",
            "c:\\program files (x86)\\windows kits\\10\\include\\10.0.22621.0\\shared\\poppack.h",
            "c:\\program files (x86)\\windows kits\\10\\include\\10.0.22621.0\\shared\\poppack.h",
            "c:\\program files (x86)\\windows kits\\10\\include\\10.0.22621.0\\um\\commdlg.h",
            "c:\\program files (x86)\\windows kits\\10\\include\\10.0.22621.0\\um\\prsht.h",
            "c:\\program files (x86)\\windows kits\\10\\include\\10.0.22621.0\\shared\\pshpack1.h",
            "c:\\program files (x86)\\windows kits\\10\\include\\10.0.22621.0\\shared\\poppack.h",
            "c:\\program files (x86)\\windows kits\\10\\include\\10.0.22621.0\\shared\\stralign.h",
            "c:\\program files (x86)\\windows kits\\10\\include\\10.0.22621.0\\um\\winsvc.h",
            "c:\\program files (x86)\\windows kits\\10\\include\\10.0.22621.0\\um\\mcx.h",
            "c:\\program files (x86)\\windows kits\\10\\include\\10.0.22621.0\\um\\imm.h",
            "c:\\program files (x86)\\windows kits\\10\\include\\10.0.22621.0\\um\\ime_cmodes.h",
            "c:\\program files\\microsoft visual studio\\2022\\community\\vc\\tools\\msvc\\14.43.34808\\include\\fstream",
            "c:\\program files\\microsoft visual studio\\2022\\community\\vc\\tools\\msvc\\14.43.34808\\include\\yvals_core.h",
            "c:\\program files\\microsoft visual studio\\2022\\community\\vc\\tools\\msvc\\14.43.34808\\include\\xkeycheck.h",
            "c:\\program files\\microsoft visual studio\\2022\\community\\vc\\tools\\msvc\\14.43.34808\\include\\__msvc_filebuf.hpp",
            "c:\\program files\\microsoft visual studio\\2022\\community\\vc\\tools\\msvc\\14.43.34808\\include\\yvals.h",
            "c:\\program files (x86)\\windows kits\\10\\include\\10.0.22621.0\\ucrt\\crtdbg.h",
            "c:\\program files\\microsoft visual studio\\2022\\community\\vc\\tools\\msvc\\14.43.34808\\include\\vcruntime_new_debug.h",
            "c:\\program files\\microsoft visual studio\\2022\\community\\vc\\tools\\msvc\\14.43.34808\\include\\vcruntime_new.h",
            "c:\\program files\\microsoft visual studio\\2022\\community\\vc\\tools\\msvc\\14.43.34808\\include\\crtdefs.h",
            "c:\\program files\\microsoft visual studio\\2022\\community\\vc\\tools\\msvc\\14.43.34808\\include\\use_ansi.h",
            "c:\\program files\\microsoft visual studio\\2022\\community\\vc\\tools\\msvc\\14.43.34808\\include\\cstdio",
            "c:\\program files (x86)\\windows kits\\10\\include\\10.0.22621.0\\ucrt\\stdio.h",
            "c:\\program files (x86)\\windows kits\\10\\include\\10.0.22621.0\\ucrt\\corecrt_wstdio.h",
            "c:\\program files (x86)\\windows kits\\10\\include\\10.0.22621.0\\ucrt\\corecrt_stdio_config.h",
            "c:\\program files\\microsoft visual studio\\2022\\community\\vc\\tools\\msvc\\14.43.34808\\include\\streambuf",
            "c:\\program files\\microsoft visual studio\\2022\\community\\vc\\tools\\msvc\\14.43.34808\\include\\xiosbase",
            "c:\\program files (x86)\\windows kits\\10\\include\\10.0.22621.0\\ucrt\\share.h",
            "c:\\program files (x86)\\windows kits\\10\\include\\10.0.22621.0\\ucrt\\corecrt_share.h",
            "c:\\program files\\microsoft visual studio\\2022\\community\\vc\\tools\\msvc\\14.43.34808\\include\\system_error",
            "c:\\program files\\microsoft visual studio\\2022\\community\\vc\\tools\\msvc\\14.43.34808\\include\\__msvc_system_error_abi.hpp",
            "c:\\program files\\microsoft visual studio\\2022\\community\\vc\\tools\\msvc\\14.43.34808\\include\\cstddef",
            "c:\\program files\\microsoft visual studio\\2022\\community\\vc\\tools\\msvc\\14.43.34808\\include\\xtr1common",
            "c:\\program files\\microsoft visual studio\\2022\\community\\vc\\tools\\msvc\\14.43.34808\\include\\cerrno",
            "c:\\program files\\microsoft visual studio\\2022\\community\\vc\\tools\\msvc\\14.43.34808\\include\\cstdlib",
            "c:\\program files (x86)\\windows kits\\10\\include\\10.0.22621.0\\ucrt\\math.h",
            "c:\\program files (x86)\\windows kits\\10\\include\\10.0.22621.0\\ucrt\\corecrt_math.h",
            "c:\\program files\\microsoft visual studio\\2022\\community\\vc\\tools\\msvc\\14.43.34808\\include\\stdexcept",
            "c:\\program files\\microsoft visual studio\\2022\\community\\vc\\tools\\msvc\\14.43.34808\\include\\exception",
            "c:\\program files\\microsoft visual studio\\2022\\community\\vc\\tools\\msvc\\14.43.34808\\include\\type_traits",
            "c:\\program files\\microsoft visual studio\\2022\\community\\vc\\tools\\msvc\\14.43.34808\\include\\cstdint",
            "c:\\program files\\microsoft visual studio\\2022\\community\\vc\\tools\\msvc\\14.43.34808\\include\\stdint.h",
            "c:\\program files\\microsoft visual studio\\2022\\community\\vc\\tools\\msvc\\14.43.34808\\include\\cstring",
            "c:\\program files (x86)\\windows kits\\10\\include\\10.0.22621.0\\ucrt\\malloc.h",
            "c:\\program files\\microsoft visual studio\\2022\\community\\vc\\tools\\msvc\\14.43.34808\\include\\vcruntime_exception.h",
            "c:\\program files\\microsoft visual studio\\2022\\community\\vc\\tools\\msvc\\14.43.34808\\include\\eh.h",
            "c:\\program files (x86)\\windows kits\\10\\include\\10.0.22621.0\\ucrt\\corecrt_terminate.h",
            "c:\\program files\\microsoft visual studio\\2022\\community\\vc\\tools\\msvc\\14.43.34808\\include\\xstring",
            "c:\\program files\\microsoft visual studio\\2022\\community\\vc\\tools\\msvc\\14.43.34808\\include\\__msvc_sanitizer_annotate_container.hpp",
            "c:\\program files\\microsoft visual studio\\2022\\community\\vc\\tools\\msvc\\14.43.34808\\include\\__msvc_string_view.hpp",
            "c:\\program files\\microsoft visual studio\\2022\\community\\vc\\tools\\msvc\\14.43.34808\\include\\iosfwd",
            "c:\\program files\\microsoft visual studio\\2022\\community\\vc\\tools\\msvc\\14.43.34808\\include\\cwchar",
            "c:\\program files (x86)\\windows kits\\10\\include\\10.0.22621.0\\ucrt\\wchar.h",
            "c:\\program files (x86)\\windows kits\\10\\include\\10.0.22621.0\\ucrt\\corecrt_wconio.h",
            "c:\\program files (x86)\\windows kits\\10\\include\\10.0.22621.0\\ucrt\\corecrt_wdirect.h",
            "c:\\program files (x86)\\windows kits\\10\\include\\10.0.22621.0\\ucrt\\corecrt_wio.h",
            "c:\\program files (x86)\\windows kits\\10\\include\\10.0.22621.0\\ucrt\\corecrt_wprocess.h",
            "c:\\program files (x86)\\windows kits\\10\\include\\10.0.22621.0\\ucrt\\corecrt_wtime.h",
            "c:\\program files (x86)\\windows kits\\10\\include\\10.0.22621.0\\ucrt\\sys\\stat.h",
            "c:\\program files (x86)\\windows kits\\10\\include\\10.0.22621.0\\ucrt\\sys\\types.h",
            "c:\\program files\\microsoft visual studio\\2022\\community\\vc\\tools\\msvc\\14.43.34808\\include\\xutility",
            "c:\\program files\\microsoft visual studio\\2022\\community\\vc\\tools\\msvc\\14.43.34808\\include\\__msvc_iter_core.hpp",
            "c:\\program files\\microsoft visual studio\\2022\\community\\vc\\tools\\msvc\\14.43.34808\\include\\utility",
            "c:\\program files\\microsoft visual studio\\2022\\community\\vc\\tools\\msvc\\14.43.34808\\include\\initializer_list",
            "c:\\program files\\microsoft visual studio\\2022\\community\\vc\\tools\\msvc\\14.43.34808\\include\\compare",
            "c:\\program files\\microsoft visual studio\\2022\\community\\vc\\tools\\msvc\\14.43.34808\\include\\concepts",
            "c:\\program files\\microsoft visual studio\\2022\\community\\vc\\tools\\msvc\\14.43.34808\\include\\climits",
            "c:\\program files\\microsoft visual studio\\2022\\community\\vc\\tools\\msvc\\14.43.34808\\include\\xmemory",
            "c:\\program files\\microsoft visual studio\\2022\\community\\vc\\tools\\msvc\\14.43.34808\\include\\limits",
            "c:\\program files\\microsoft visual studio\\2022\\community\\vc\\tools\\msvc\\14.43.34808\\include\\cfloat",
            "c:\\program files (x86)\\windows kits\\10\\include\\10.0.22621.0\\ucrt\\float.h",
            "c:\\program files\\microsoft visual studio\\2022\\community\\vc\\tools\\msvc\\14.43.34808\\include\\intrin0.h",
            "c:\\program files\\microsoft visual studio\\2022\\community\\vc\\tools\\msvc\\14.43.34808\\include\\intrin0.inl.h",
            "c:\\program files\\microsoft visual studio\\2022\\community\\vc\\tools\\msvc\\14.43.34808\\include\\new",
            "c:\\program files\\microsoft visual studio\\2022\\community\\vc\\tools\\msvc\\14.43.34808\\include\\xatomic.h",
            "c:\\program files\\microsoft visual studio\\2022\\community\\vc\\tools\\msvc\\14.43.34808\\include\\tuple",
            "c:\\program files\\microsoft visual studio\\2022\\community\\vc\\tools\\msvc\\14.43.34808\\include\\xpolymorphic_allocator.h",
            "c:\\program files\\microsoft visual studio\\2022\\community\\vc\\tools\\msvc\\14.43.34808\\include\\xcall_once.h",
            "c:\\program files\\microsoft visual studio\\2022\\community\\vc\\tools\\msvc\\14.43.34808\\include\\xerrc.h",
            "c:\\program files\\microsoft visual studio\\2022\\community\\vc\\tools\\msvc\\14.43.34808\\include\\atomic",
            "c:\\program files\\microsoft visual studio\\2022\\community\\vc\\tools\\msvc\\14.43.34808\\include\\xatomic_wait.h",
            "c:\\program files\\microsoft visual studio\\2022\\community\\vc\\tools\\msvc\\14.43.34808\\include\\xthreads.h",
            "c:\\program files\\microsoft visual studio\\2022\\community\\vc\\tools\\msvc\\14.43.34808\\include\\__msvc_threads_core.hpp",
            "c:\\program files\\microsoft visual studio\\2022\\community\\vc\\tools\\msvc\\14.43.34808\\include\\xtimec.h",
            "c:\\program files\\microsoft visual studio\\2022\\community\\vc\\tools\\msvc\\14.43.34808\\include\\ctime",
            "c:\\program files (x86)\\windows kits\\10\\include\\10.0.22621.0\\ucrt\\time.h",
            "c:\\program files\\microsoft visual studio\\2022\\community\\vc\\tools\\msvc\\14.43.34808\\include\\xlocale",
            "c:\\program files\\microsoft visual studio\\2022\\community\\vc\\tools\\msvc\\14.43.34808\\include\\memory",
            "c:\\program files\\microsoft visual studio\\2022\\community\\vc\\tools\\msvc\\14.43.34808\\include\\typeinfo",
            "c:\\program files\\microsoft visual studio\\2022\\community\\vc\\tools\\msvc\\14.43.34808\\include\\vcruntime_typeinfo.h",
            "c:\\program files\\microsoft visual studio\\2022\\community\\vc\\tools\\msvc\\14.43.34808\\include\\xfacet",
            "c:\\program files\\microsoft visual studio\\2022\\community\\vc\\tools\\msvc\\14.43.34808\\include\\xlocinfo",
            "c:\\program files\\microsoft visual studio\\2022\\community\\vc\\tools\\msvc\\14.43.34808\\include\\__msvc_xlocinfo_types.hpp",
            "c:\\program files\\microsoft visual studio\\2022\\community\\vc\\tools\\msvc\\14.43.34808\\include\\cctype",
            "c:\\program files\\microsoft visual studio\\2022\\community\\vc\\tools\\msvc\\14.43.34808\\include\\clocale",
            "c:\\program files (x86)\\windows kits\\10\\include\\10.0.22621.0\\ucrt\\locale.h",
            "c:\\program files\\microsoft visual studio\\2022\\community\\vc\\tools\\msvc\\14.43.34808\\include\\istream",
            "c:\\program files\\microsoft visual studio\\2022\\community\\vc\\tools\\msvc\\14.43.34808\\include\\__msvc_ostream.hpp",
            "c:\\program files\\microsoft visual studio\\2022\\community\\vc\\tools\\msvc\\14.43.34808\\include\\ios",
            "c:\\program files\\microsoft visual studio\\2022\\community\\vc\\tools\\msvc\\14.43.34808\\include\\xlocnum",
            "c:\\program files\\microsoft visual studio\\2022\\community\\vc\\tools\\msvc\\14.43.34808\\include\\cmath",
            "c:\\program files\\microsoft visual studio\\2022\\community\\vc\\tools\\msvc\\14.43.34808\\include\\iterator",
            "c:\\program files\\microsoft visual studio\\2022\\community\\vc\\tools\\msvc\\14.43.34808\\include\\format",
            "c:\\program files\\microsoft visual studio\\2022\\community\\vc\\tools\\msvc\\14.43.34808\\include\\__msvc_format_ucd_tables.hpp",
            "c:\\program files\\microsoft visual studio\\2022\\community\\vc\\tools\\msvc\\14.43.34808\\include\\__msvc_formatter.hpp",
            "c:\\program files\\microsoft visual studio\\2022\\community\\vc\\tools\\msvc\\14.43.34808\\include\\__msvc_print.hpp",
            "c:\\program files\\microsoft visual studio\\2022\\community\\vc\\tools\\msvc\\14.43.34808\\include\\xfilesystem_abi.h",
            "c:\\program files\\microsoft visual studio\\2022\\community\\vc\\tools\\msvc\\14.43.34808\\include\\__msvc_ranges_tuple_formatter.hpp",
            "c:\\program files\\microsoft visual studio\\2022\\community\\vc\\tools\\msvc\\14.43.34808\\include\\bit",
            "c:\\program files\\microsoft visual studio\\2022\\community\\vc\\tools\\msvc\\14.43.34808\\include\\__msvc_bit_utils.hpp",
            "c:\\program files\\microsoft visual studio\\2022\\community\\vc\\tools\\msvc\\14.43.34808\\include\\charconv",
            "c:\\program files\\microsoft visual studio\\2022\\community\\vc\\tools\\msvc\\14.43.34808\\include\\xbit_ops.h",
            "c:\\program files\\microsoft visual studio\\2022\\community\\vc\\tools\\msvc\\14.43.34808\\include\\xcharconv.h",
            "c:\\program files\\microsoft visual studio\\2022\\community\\vc\\tools\\msvc\\14.43.34808\\include\\xcharconv_ryu.h",
            "c:\\program files\\microsoft visual studio\\2022\\community\\vc\\tools\\msvc\\14.43.34808\\include\\xcharconv_ryu_tables.h",
            "c:\\program files\\microsoft visual studio\\2022\\community\\vc\\tools\\msvc\\14.43.34808\\include\\xcharconv_tables.h",
            "c:\\program files\\microsoft visual studio\\2022\\community\\vc\\tools\\msvc\\14.43.34808\\include\\locale",
            "c:\\program files\\microsoft visual studio\\2022\\community\\vc\\tools\\msvc\\14.43.34808\\include\\xlocbuf",
            "c:\\program files\\microsoft visual studio\\2022\\community\\vc\\tools\\msvc\\14.43.34808\\include\\xlocmes",
            "c:\\program files\\microsoft visual studio\\2022\\community\\vc\\tools\\msvc\\14.43.34808\\include\\xlocmon",
            "c:\\program files\\microsoft visual studio\\2022\\community\\vc\\tools\\msvc\\14.43.34808\\include\\xloctime",
            "c:\\users\\oli\\documents\\github\\abot-master\\1.0\\libs\\cocos-headers\\cocos2dx\\include\\cocos2d.h",
            "c:\\users\\oli\\documents\\github\\abot-master\\1.0\\libs\\cocos-headers\\cocos2dx\\include\\ccconfig.h",
            "c:\\users\\oli\\documents\\github\\abot-master\\1.0\\libs\\cocos-headers\\cocos2dx\\platform\\ccplatformconfig.h",
            "c:\\users\\oli\\documents\\github\\abot-master\\1.0\\libs\\cocos-headers\\cocos2dx\\actions\\ccaction.h",
            "c:\\users\\oli\\documents\\github\\abot-master\\1.0\\libs\\cocos-headers\\cocos2dx\\cocoa\\ccobject.h",
            "c:\\users\\oli\\documents\\github\\abot-master\\1.0\\libs\\cocos-headers\\cocos2dx\\cocoa\\ccdatavisitor.h",
            "c:\\users\\oli\\documents\\github\\abot-master\\1.0\\libs\\cocos-headers\\cocos2dx\\platform\\ccplatformmacros.h",
            "c:\\users\\oli\\documents\\github\\abot-master\\1.0\\libs\\cocos-headers\\cocos2dx\\platform\\win32\\ccplatformdefine.h",
            "c:\\program files (x86)\\windows kits\\10\\include\\10.0.22621.0\\ucrt\\assert.h",
            "c:\\program files\\microsoft visual studio\\2022\\community\\vc\\tools\\msvc\\14.43.34808\\include\\string",
            "c:\\users\\oli\\documents\\github\\abot-master\\1.0\\libs\\cocos-headers\\cocos2dx\\include\\ccmacros.h",
            "c:\\users\\oli\\documents\\github\\abot-master\\1.0\\libs\\cocos-headers\\cocos2dx\\platform\\cccommon.h",
            "c:\\users\\oli\\documents\\github\\abot-master\\1.0\\libs\\cocos-headers\\cocos2dx\\platform\\win32\\ccstdc.h",
            "c:\\program files (x86)\\windows kits\\10\\include\\10.0.22621.0\\ucrt\\math.h",
            "c:\\program files (x86)\\windows kits\\10\\include\\10.0.22621.0\\ucrt\\corecrt_math_defines.h",
            "c:\\users\\oli\\documents\\github\\abot-master\\1.0\\libs\\cocos-headers\\cocos2dx\\cocoa\\ccgeometry.h",
            "c:\\program files (x86)\\windows kits\\10\\include\\10.0.22621.0\\ucrt\\math.h",
            "c:\\users\\oli\\documents\\github\\abot-master\\1.0\\libs\\cocos-headers\\cocos2dx\\actions\\ccactioninterval.h",
            "c:\\users\\oli\\documents\\github\\abot-master\\1.0\\libs\\cocos-headers\\cocos2dx\\base_nodes\\ccnode.h",
            "c:\\users\\oli\\documents\\github\\abot-master\\1.0\\libs\\cocos-headers\\cocos2dx\\cocoa\\ccaffinetransform.h",
            "c:\\users\\oli\\documents\\github\\abot-master\\1.0\\libs\\cocos-headers\\cocos2dx\\cocoa\\ccarray.h",
            "c:\\users\\oli\\documents\\github\\abot-master\\1.0\\libs\\cocos-headers\\cocos2dx\\support\\data_support\\cccarray.h",
            "c:\\users\\oli\\documents\\github\\abot-master\\1.0\\libs\\cocos-headers\\cocos2dx\\platform\\win32\\ccgl.h",
            "c:\\users\\oli\\documents\\github\\abot-master\\1.0\\libs\\cocos-headers\\cocos2dx\\platform\\third_party\\win32\\ogles\\gl\\glew.h",
            "c:\\program files (x86)\\windows kits\\10\\include\\10.0.22621.0\\um\\gl\\glu.h",
            "c:\\program files (x86)\\windows kits\\10\\include\\10.0.22621.0\\um\\gl\\gl.h",
            "c:\\users\\oli\\documents\\github\\abot-master\\1.0\\libs\\cocos-headers\\cocos2dx\\shaders\\ccglstatecache.h",
            "c:\\users\\oli\\documents\\github\\abot-master\\1.0\\libs\\cocos-headers\\cocos2dx\\shaders\\ccglprogram.h",
            "c:\\users\\oli\\documents\\github\\abot-master\\1.0\\libs\\cocos-headers\\cocos2dx\\kazmath\\include\\kazmath\\kazmath.h",
            "c:\\users\\oli\\documents\\github\\abot-master\\1.0\\libs\\cocos-headers\\cocos2dx\\kazmath\\include\\kazmath\\vec2.h",
            "c:\\users\\oli\\documents\\github\\abot-master\\1.0\\libs\\cocos-headers\\cocos2dx\\kazmath\\include\\kazmath\\vec3.h",
            "c:\\program files (x86)\\windows kits\\10\\include\\10.0.22621.0\\ucrt\\assert.h",
            "c:\\users\\oli\\documents\\github\\abot-master\\1.0\\libs\\cocos-headers\\cocos2dx\\kazmath\\include\\kazmath\\mat3.h",
            "c:\\users\\oli\\documents\\github\\abot-master\\1.0\\libs\\cocos-headers\\cocos2dx\\kazmath\\include\\kazmath\\utility.h",
            "c:\\program files (x86)\\windows kits\\10\\include\\10.0.22621.0\\ucrt\\math.h",
            "c:\\users\\oli\\documents\\github\\abot-master\\1.0\\libs\\cocos-headers\\cocos2dx\\kazmath\\include\\kazmath\\mat4.h",
            "c:\\users\\oli\\documents\\github\\abot-master\\1.0\\libs\\cocos-headers\\cocos2dx\\kazmath\\include\\kazmath\\quaternion.h",
            "c:\\users\\oli\\documents\\github\\abot-master\\1.0\\libs\\cocos-headers\\cocos2dx\\kazmath\\include\\kazmath\\plane.h",
            "c:\\users\\oli\\documents\\github\\abot-master\\1.0\\libs\\cocos-headers\\cocos2dx\\kazmath\\include\\kazmath\\aabb.h",
            "c:\\users\\oli\\documents\\github\\abot-master\\1.0\\libs\\cocos-headers\\cocos2dx\\kazmath\\include\\kazmath\\ray2.h",
            "c:\\users\\oli\\documents\\github\\abot-master\\1.0\\libs\\cocos-headers\\cocos2dx\\script_support\\ccscriptsupport.h",
            "c:\\users\\oli\\documents\\github\\abot-master\\1.0\\libs\\cocos-headers\\cocos2dx\\platform\\win32\\ccaccelerometer.h",
            "c:\\users\\oli\\documents\\github\\abot-master\\1.0\\libs\\cocos-headers\\cocos2dx\\platform\\ccaccelerometerdelegate.h",
            "c:\\users\\oli\\documents\\github\\abot-master\\1.0\\libs\\cocos-headers\\cocos2dx\\touch_dispatcher\\cctouch.h",
            "c:\\users\\oli\\documents\\github\\abot-master\\1.0\\libs\\cocos-headers\\cocos2dx\\cocoa\\ccset.h",
            "c:\\program files\\microsoft visual studio\\2022\\community\\vc\\tools\\msvc\\14.43.34808\\include\\set",
            "c:\\program files\\microsoft visual studio\\2022\\community\\vc\\tools\\msvc\\14.43.34808\\include\\xtree",
            "c:\\program files\\microsoft visual studio\\2022\\community\\vc\\tools\\msvc\\14.43.34808\\include\\xnode_handle.h",
            "c:\\program files\\microsoft visual studio\\2022\\community\\vc\\tools\\msvc\\14.43.34808\\include\\map",
            "c:\\program files\\microsoft visual studio\\2022\\community\\vc\\tools\\msvc\\14.43.34808\\include\\list",
            "c:\\users\\oli\\documents\\github\\abot-master\\1.0\\libs\\cocos-headers\\cocos2dx\\include\\ccprotocols.h",
            "c:\\users\\oli\\documents\\github\\abot-master\\1.0\\libs\\cocos-headers\\cocos2dx\\include\\cctypes.h",
            "c:\\users\\oli\\documents\\github\\abot-master\\1.0\\libs\\cocos-headers\\cocos2dx\\textures\\cctexture2d.h",
            "c:\\users\\oli\\documents\\github\\abot-master\\1.0\\libs\\cocos-headers\\cocos2dx\\sprite_nodes\\ccspriteframe.h",
            "c:\\users\\oli\\documents\\github\\abot-master\\1.0\\libs\\cocos-headers\\cocos2dx\\sprite_nodes\\ccanimation.h",
            "c:\\users\\oli\\documents\\github\\abot-master\\1.0\\libs\\cocos-headers\\cocos2dx\\cocoa\\ccdictionary.h",
            "c:\\users\\oli\\documents\\github\\abot-master\\1.0\\libs\\cocos-headers\\cocos2dx\\support\\data_support\\uthash.h",
            "c:\\users\\oli\\documents\\github\\abot-master\\1.0\\libs\\cocos-headers\\cocos2dx\\cocoa\\ccstring.h",
            "c:\\program files\\microsoft visual studio\\2022\\community\\vc\\tools\\msvc\\14.43.34808\\include\\functional",
            "c:\\program files\\microsoft visual studio\\2022\\community\\vc\\tools\\msvc\\14.43.34808\\include\\unordered_map",
            "c:\\program files\\microsoft visual studio\\2022\\community\\vc\\tools\\msvc\\14.43.34808\\include\\xhash",
            "c:\\program files\\microsoft visual studio\\2022\\community\\vc\\tools\\msvc\\14.43.34808\\include\\vector",
            "c:\\users\\oli\\documents\\github\\abot-master\\1.0\\libs\\cocos-headers\\cocos2dx\\actions\\ccactioncamera.h",
            "c:\\users\\oli\\documents\\github\\abot-master\\1.0\\libs\\cocos-headers\\cocos2dx\\actions\\ccactionmanager.h",
            "c:\\users\\oli\\documents\\github\\abot-master\\1.0\\libs\\cocos-headers\\cocos2dx\\actions\\ccactionease.h",
            "c:\\users\\oli\\documents\\github\\abot-master\\1.0\\libs\\cocos-headers\\cocos2dx\\actions\\ccactionpageturn3d.h",
            "c:\\users\\oli\\documents\\github\\abot-master\\1.0\\libs\\cocos-headers\\cocos2dx\\actions\\ccactiongrid3d.h",
            "c:\\users\\oli\\documents\\github\\abot-master\\1.0\\libs\\cocos-headers\\cocos2dx\\actions\\ccactiongrid.h",
            "c:\\users\\oli\\documents\\github\\abot-master\\1.0\\libs\\cocos-headers\\cocos2dx\\actions\\ccactioninstant.h",
            "c:\\users\\oli\\documents\\github\\abot-master\\1.0\\libs\\cocos-headers\\cocos2dx\\include\\cctypeinfo.h",
            "c:\\users\\oli\\documents\\github\\abot-master\\1.0\\libs\\cocos-headers\\cocos2dx\\actions\\ccactionprogresstimer.h",
            "c:\\users\\oli\\documents\\github\\abot-master\\1.0\\libs\\cocos-headers\\cocos2dx\\actions\\ccactiontiledgrid.h",
            "c:\\users\\oli\\documents\\github\\abot-master\\1.0\\libs\\cocos-headers\\cocos2dx\\actions\\ccactiontween.h",
            "c:\\users\\oli\\documents\\github\\abot-master\\1.0\\libs\\cocos-headers\\cocos2dx\\actions\\ccactioncatmullrom.h",
            "c:\\users\\oli\\documents\\github\\abot-master\\1.0\\libs\\cocos-headers\\cocos2dx\\base_nodes\\ccatlasnode.h",
            "c:\\users\\oli\\documents\\github\\abot-master\\1.0\\libs\\cocos-headers\\cocos2dx\\cocoa\\ccautoreleasepool.h",
            "c:\\users\\oli\\documents\\github\\abot-master\\1.0\\libs\\cocos-headers\\cocos2dx\\cocoa\\ccinteger.h",
            "c:\\users\\oli\\documents\\github\\abot-master\\1.0\\libs\\cocos-headers\\cocos2dx\\cocoa\\ccfloat.h",
            "c:\\users\\oli\\documents\\github\\abot-master\\1.0\\libs\\cocos-headers\\cocos2dx\\cocoa\\ccdouble.h",
            "c:\\users\\oli\\documents\\github\\abot-master\\1.0\\libs\\cocos-headers\\cocos2dx\\cocoa\\ccbool.h",
            "c:\\users\\oli\\documents\\github\\abot-master\\1.0\\libs\\cocos-headers\\cocos2dx\\cocoa\\ccns.h",
            "c:\\users\\oli\\documents\\github\\abot-master\\1.0\\libs\\cocos-headers\\cocos2dx\\cocoa\\cczone.h",
            "c:\\users\\oli\\documents\\github\\abot-master\\1.0\\libs\\cocos-headers\\cocos2dx\\draw_nodes\\ccdrawingprimitives.h",
            "c:\\users\\oli\\documents\\github\\abot-master\\1.0\\libs\\cocos-headers\\cocos2dx\\draw_nodes\\ccdrawnode.h",
            "c:\\users\\oli\\documents\\github\\abot-master\\1.0\\libs\\cocos-headers\\cocos2dx\\effects\\ccgrabber.h",
            "c:\\users\\oli\\documents\\github\\abot-master\\1.0\\libs\\cocos-headers\\cocos2dx\\ccconfiguration.h",
            "c:\\users\\oli\\documents\\github\\abot-master\\1.0\\libs\\cocos-headers\\cocos2dx\\effects\\ccgrid.h",
            "c:\\users\\oli\\documents\\github\\abot-master\\1.0\\libs\\cocos-headers\\cocos2dx\\cccamera.h",
            "c:\\users\\oli\\documents\\github\\abot-master\\1.0\\libs\\cocos-headers\\cocos2dx\\ccdirector.h",
            "c:\\users\\oli\\documents\\github\\abot-master\\1.0\\libs\\cocos-headers\\cocos2dx\\label_nodes\\cclabelatlas.h",
            "c:\\users\\oli\\documents\\github\\abot-master\\1.0\\libs\\cocos-headers\\cocos2dx\\include\\cceventtype.h",
            "c:\\users\\oli\\documents\\github\\abot-master\\1.0\\libs\\cocos-headers\\cocos2dx\\kazmath\\include\\kazmath\\gl\\matrix.h",
            "c:\\users\\oli\\documents\\github\\abot-master\\1.0\\libs\\cocos-headers\\cocos2dx\\keypad_dispatcher\\cckeypaddelegate.h",
            "c:\\users\\oli\\documents\\github\\abot-master\\1.0\\libs\\cocos-headers\\cocos2dx\\keypad_dispatcher\\cckeypaddispatcher.h",
            "c:\\users\\oli\\documents\\github\\abot-master\\1.0\\libs\\cocos-headers\\cocos2dx\\label_nodes\\cclabelttf.h",
            "c:\\users\\oli\\documents\\github\\abot-master\\1.0\\libs\\cocos-headers\\cocos2dx\\sprite_nodes\\ccsprite.h",
            "c:\\users\\oli\\documents\\github\\abot-master\\1.0\\libs\\cocos-headers\\cocos2dx\\textures\\cctextureatlas.h",
            "c:\\users\\oli\\documents\\github\\abot-master\\1.0\\libs\\cocos-headers\\cocos2dx\\label_nodes\\cclabelbmfont.h",
            "c:\\users\\oli\\documents\\github\\abot-master\\1.0\\libs\\cocos-headers\\cocos2dx\\sprite_nodes\\ccspritebatchnode.h",
            "c:\\program files\\microsoft visual studio\\2022\\community\\vc\\tools\\msvc\\14.43.34808\\include\\sstream",
            "c:\\program files\\microsoft visual studio\\2022\\community\\vc\\tools\\msvc\\14.43.34808\\include\\iostream",
            "c:\\program files\\microsoft visual studio\\2022\\community\\vc\\tools\\msvc\\14.43.34808\\include\\ostream",
            "c:\\users\\oli\\documents\\github\\abot-master\\1.0\\libs\\cocos-headers\\cocos2dx\\layers_scenes_transitions_nodes\\cclayer.h",
            "c:\\users\\oli\\documents\\github\\abot-master\\1.0\\libs\\cocos-headers\\cocos2dx\\touch_dispatcher\\cctouchdelegateprotocol.h",
            "c:\\users\\oli\\documents\\github\\abot-master\\1.0\\libs\\cocos-headers\\cocos2dx\\robtop\\keyboard_dispatcher\\cckeyboarddelegate.h",
            "c:\\users\\oli\\documents\\github\\abot-master\\1.0\\libs\\cocos-headers\\cocos2dx\\robtop\\mouse_dispatcher\\ccmousedelegate.h",
            "c:\\users\\oli\\documents\\github\\abot-master\\1.0\\libs\\cocos-headers\\cocos2dx\\layers_scenes_transitions_nodes\\ccscene.h",
            "c:\\users\\oli\\documents\\github\\abot-master\\1.0\\libs\\cocos-headers\\cocos2dx\\layers_scenes_transitions_nodes\\cctransition.h",
            "c:\\users\\oli\\documents\\github\\abot-master\\1.0\\libs\\cocos-headers\\cocos2dx\\layers_scenes_transitions_nodes\\cctransitionpageturn.h",
            "c:\\users\\oli\\documents\\github\\abot-master\\1.0\\libs\\cocos-headers\\cocos2dx\\layers_scenes_transitions_nodes\\cctransitionprogress.h",
            "c:\\users\\oli\\documents\\github\\abot-master\\1.0\\libs\\cocos-headers\\cocos2dx\\menu_nodes\\ccmenu.h",
            "c:\\users\\oli\\documents\\github\\abot-master\\1.0\\libs\\cocos-headers\\cocos2dx\\menu_nodes\\ccmenuitem.h",
            "c:\\users\\oli\\documents\\github\\abot-master\\1.0\\libs\\cocos-headers\\cocos2dx\\misc_nodes\\ccclippingnode.h",
            "c:\\users\\oli\\documents\\github\\abot-master\\1.0\\libs\\cocos-headers\\cocos2dx\\misc_nodes\\ccmotionstreak.h",
            "c:\\users\\oli\\documents\\github\\abot-master\\1.0\\libs\\cocos-headers\\cocos2dx\\misc_nodes\\ccprogresstimer.h",
            "c:\\users\\oli\\documents\\github\\abot-master\\1.0\\libs\\cocos-headers\\cocos2dx\\misc_nodes\\ccrendertexture.h",
            "c:\\users\\oli\\documents\\github\\abot-master\\1.0\\libs\\cocos-headers\\cocos2dx\\particle_nodes\\ccparticlebatchnode.h",
            "c:\\users\\oli\\documents\\github\\abot-master\\1.0\\libs\\cocos-headers\\cocos2dx\\particle_nodes\\ccparticlesystem.h",
            "c:\\users\\oli\\documents\\github\\abot-master\\1.0\\libs\\cocos-headers\\cocos2dx\\particle_nodes\\ccparticleexamples.h",
            "c:\\users\\oli\\documents\\github\\abot-master\\1.0\\libs\\cocos-headers\\cocos2dx\\particle_nodes\\ccparticlesystemquad.h",
            "c:\\users\\oli\\documents\\github\\abot-master\\1.0\\libs\\cocos-headers\\cocos2dx\\platform\\ccdevice.h",
            "c:\\users\\oli\\documents\\github\\abot-master\\1.0\\libs\\cocos-headers\\cocos2dx\\platform\\ccfileutils.h",
            "c:\\users\\oli\\documents\\github\\abot-master\\1.0\\libs\\cocos-headers\\cocos2dx\\platform\\ccimage.h",
            "c:\\users\\oli\\documents\\github\\abot-master\\1.0\\libs\\cocos-headers\\cocos2dx\\platform\\ccsaxparser.h",
            "c:\\users\\oli\\documents\\github\\abot-master\\1.0\\libs\\cocos-headers\\cocos2dx\\platform\\ccthread.h",
            "c:\\users\\oli\\documents\\github\\abot-master\\1.0\\libs\\cocos-headers\\cocos2dx\\platform\\platform.h",
            "c:\\users\\oli\\documents\\github\\abot-master\\1.0\\libs\\cocos-headers\\cocos2dx\\platform\\win32\\ccapplication.h",
            "c:\\users\\oli\\documents\\github\\abot-master\\1.0\\libs\\cocos-headers\\cocos2dx\\platform\\ccapplicationprotocol.h",
            "c:\\users\\oli\\documents\\github\\abot-master\\1.0\\libs\\cocos-headers\\cocos2dx\\platform\\win32\\cceglview.h",
            "c:\\users\\oli\\documents\\github\\abot-master\\1.0\\libs\\cocos-headers\\cocos2dx\\platform\\cceglviewprotocol.h",
            "c:\\users\\oli\\documents\\github\\abot-master\\1.0\\libs\\cocos-headers\\cocos2dx\\robtop\\glfw\\glfw3.h",
            "c:\\program files (x86)\\windows kits\\10\\include\\10.0.22621.0\\um\\gl\\gl.h",
            "c:\\users\\oli\\documents\\github\\abot-master\\1.0\\libs\\cocos-headers\\cocos2dx\\shaders\\ccshadercache.h",
            "c:\\users\\oli\\documents\\github\\abot-master\\1.0\\libs\\cocos-headers\\cocos2dx\\shaders\\ccshaders.h",
            "c:\\users\\oli\\documents\\github\\abot-master\\1.0\\libs\\cocos-headers\\cocos2dx\\sprite_nodes\\ccanimationcache.h",
            "c:\\users\\oli\\documents\\github\\abot-master\\1.0\\libs\\cocos-headers\\cocos2dx\\sprite_nodes\\ccspriteframecache.h",
            "c:\\users\\oli\\documents\\github\\abot-master\\1.0\\libs\\cocos-headers\\cocos2dx\\support\\ccutf8.h",
            "c:\\users\\oli\\documents\\github\\abot-master\\1.0\\libs\\cocos-headers\\cocos2dx\\support\\ccnotificationcenter.h",
            "c:\\users\\oli\\documents\\github\\abot-master\\1.0\\libs\\cocos-headers\\cocos2dx\\support\\ccpointextension.h",
            "c:\\program files (x86)\\windows kits\\10\\include\\10.0.22621.0\\ucrt\\math.h",
            "c:\\users\\oli\\documents\\github\\abot-master\\1.0\\libs\\cocos-headers\\cocos2dx\\support\\ccprofiling.h",
            "c:\\users\\oli\\documents\\github\\abot-master\\1.0\\libs\\cocos-headers\\cocos2dx\\support\\user_default\\ccuserdefault.h",
            "c:\\users\\oli\\documents\\github\\abot-master\\1.0\\libs\\cocos-headers\\cocos2dx\\support\\ccvertex.h",
            "c:\\users\\oli\\documents\\github\\abot-master\\1.0\\libs\\cocos-headers\\cocos2dx\\support\\tinyxml2\\tinyxml2.h",
            "c:\\program files\\microsoft visual studio\\2022\\community\\vc\\tools\\msvc\\14.43.34808\\include\\cstdarg",
            "c:\\users\\oli\\documents\\github\\abot-master\\1.0\\libs\\cocos-headers\\cocos2dx\\text_input_node\\ccimedelegate.h",
            "c:\\users\\oli\\documents\\github\\abot-master\\1.0\\libs\\cocos-headers\\cocos2dx\\text_input_node\\ccimedispatcher.h",
            "c:\\users\\oli\\documents\\github\\abot-master\\1.0\\libs\\cocos-headers\\cocos2dx\\text_input_node\\cctextfieldttf.h",
            "c:\\users\\oli\\documents\\github\\abot-master\\1.0\\libs\\cocos-headers\\cocos2dx\\textures\\cctexturecache.h",
            "c:\\users\\oli\\documents\\github\\abot-master\\1.0\\libs\\cocos-headers\\cocos2dx\\textures\\cctexturepvr.h",
            "c:\\users\\oli\\documents\\github\\abot-master\\1.0\\libs\\cocos-headers\\cocos2dx\\tilemap_parallax_nodes\\ccparallaxnode.h",
            "c:\\users\\oli\\documents\\github\\abot-master\\1.0\\libs\\cocos-headers\\cocos2dx\\tilemap_parallax_nodes\\cctmxlayer.h",
            "c:\\users\\oli\\documents\\github\\abot-master\\1.0\\libs\\cocos-headers\\cocos2dx\\tilemap_parallax_nodes\\cctmxobjectgroup.h",
            "c:\\users\\oli\\documents\\github\\abot-master\\1.0\\libs\\cocos-headers\\cocos2dx\\tilemap_parallax_nodes\\cctmxxmlparser.h",
            "c:\\users\\oli\\documents\\github\\abot-master\\1.0\\libs\\cocos-headers\\cocos2dx\\tilemap_parallax_nodes\\cctmxtiledmap.h",
            "c:\\users\\oli\\documents\\github\\abot-master\\1.0\\libs\\cocos-headers\\cocos2dx\\tilemap_parallax_nodes\\cctilemapatlas.h",
            "c:\\users\\oli\\documents\\github\\abot-master\\1.0\\libs\\cocos-headers\\cocos2dx\\touch_dispatcher\\cctouchdispatcher.h",
            "c:\\users\\oli\\documents\\github\\abot-master\\1.0\\libs\\cocos-headers\\cocos2dx\\touch_dispatcher\\cctouchhandler.h",
            "c:\\users\\oli\\documents\\github\\abot-master\\1.0\\libs\\cocos-headers\\cocos2dx\\ccscheduler.h",
            "c:\\users\\oli\\documents\\github\\abot-master\\1.0\\libs\\cocos-headers\\cocos2dx\\support\\component\\cccomponent.h",
            "c:\\users\\oli\\documents\\github\\abot-master\\1.0\\libs\\cocos-headers\\cocos2dx\\support\\component\\cccomponentcontainer.h",
            "c:\\users\\oli\\documents\\github\\abot-master\\1.0\\libs\\cocos-headers\\cocos2dx\\robtop\\keyboard_dispatcher\\cckeyboarddispatcher.h",
            "c:\\users\\oli\\documents\\github\\abot-master\\1.0\\libs\\cocos-headers\\cocos2dx\\robtop\\mouse_dispatcher\\ccmousedispatcher.h",
            "c:\\users\\oli\\documents\\github\\abot-master\\1.0\\libs\\cocos-headers\\cocos2dx\\robtop\\scene_nodes\\ccscenetransitiondelegate.h",
            "c:\\users\\oli\\documents\\github\\abot-master\\1.0\\libs\\cocos-headers\\cocos2dx\\robtop\\xml\\ds_dictionary.h",
            "c:\\users\\oli\\documents\\github\\abot-master\\1.0\\libs\\cocos-headers\\cocos2dx\\robtop\\xml\\pugixml.hpp",
            "c:\\users\\oli\\documents\\github\\abot-master\\1.0\\libs\\cocos-headers\\cocos2dx\\include\\cocos2d.h",
            "c:\\users\\oli\\documents\\github\\abot-master\\1.0\\libs\\cocos-headers\\cocos2dx\\robtop\\xml\\pugiconfig.hpp",
            "c:\\users\\oli\\documents\\github\\abot-master\\1.0\\libs\\cocos-headers\\cocos2dx\\include\\cocos2d.h",
            "c:\\users\\oli\\documents\\github\\abot-master\\1.0\\libs\\gd.h\\include\\gd.h",
            "c:\\users\\oli\\documents\\github\\abot-master\\1.0\\libs\\cocos-headers\\extensions\\cocos-ext.h",
            "c:\\users\\oli\\documents\\github\\abot-master\\1.0\\libs\\cocos-headers\\extensions\\extensionmacros.h",
            "c:\\users\\oli\\documents\\github\\abot-master\\1.0\\libs\\cocos-headers\\extensions\\gui\\cccontrolextension\\cccontrolextensions.h",
            "c:\\users\\oli\\documents\\github\\abot-master\\1.0\\libs\\cocos-headers\\extensions\\gui\\cccontrolextension\\ccscale9sprite.h",
            "c:\\users\\oli\\documents\\github\\abot-master\\1.0\\libs\\cocos-headers\\extensions\\gui\\cccontrolextension\\cccontrol.h",
            "c:\\users\\oli\\documents\\github\\abot-master\\1.0\\libs\\cocos-headers\\extensions\\gui\\cccontrolextension\\ccinvocation.h",
            "c:\\users\\oli\\documents\\github\\abot-master\\1.0\\libs\\cocos-headers\\extensions\\gui\\cccontrolextension\\cccontrolutils.h",
            "c:\\users\\oli\\documents\\github\\abot-master\\1.0\\libs\\cocos-headers\\extensions\\gui\\cccontrolextension\\cccontrolbutton.h",
            "c:\\users\\oli\\documents\\github\\abot-master\\1.0\\libs\\cocos-headers\\extensions\\gui\\cccontrolextension\\cccontrolcolourpicker.h",
            "c:\\users\\oli\\documents\\github\\abot-master\\1.0\\libs\\cocos-headers\\extensions\\gui\\cccontrolextension\\cccontrolhuepicker.h",
            "c:\\users\\oli\\documents\\github\\abot-master\\1.0\\libs\\cocos-headers\\extensions\\gui\\cccontrolextension\\cccontrolsaturationbrightnesspicker.h",
            "c:\\users\\oli\\documents\\github\\abot-master\\1.0\\libs\\cocos-headers\\extensions\\gui\\cccontrolextension\\colorpickerdelegate.h",
            "c:\\users\\oli\\documents\\github\\abot-master\\1.0\\libs\\cocos-headers\\extensions\\gui\\cccontrolextension\\cccontrolpotentiometer.h",
            "c:\\users\\oli\\documents\\github\\abot-master\\1.0\\libs\\cocos-headers\\extensions\\gui\\cccontrolextension\\cccontrolslider.h",
            "c:\\users\\oli\\documents\\github\\abot-master\\1.0\\libs\\cocos-headers\\extensions\\gui\\cccontrolextension\\cccontrolstepper.h",
            "c:\\users\\oli\\documents\\github\\abot-master\\1.0\\libs\\cocos-headers\\extensions\\gui\\cccontrolextension\\cccontrolswitch.h",
            "c:\\users\\oli\\documents\\github\\abot-master\\1.0\\libs\\cocos-headers\\extensions\\gui\\ccscrollview\\ccscrollview.h",
            "c:\\users\\oli\\documents\\github\\abot-master\\1.0\\libs\\cocos-headers\\extensions\\gui\\ccscrollview\\cctableview.h",
            "c:\\users\\oli\\documents\\github\\abot-master\\1.0\\libs\\cocos-headers\\extensions\\gui\\ccscrollview\\cctableviewcell.h",
            "c:\\users\\oli\\documents\\github\\abot-master\\1.0\\libs\\cocos-headers\\extensions\\gui\\ccscrollview\\ccsorting.h",
            "c:\\users\\oli\\documents\\github\\abot-master\\1.0\\libs\\cocos-headers\\extensions\\gui\\cceditbox\\cceditbox.h",
            "c:\\users\\oli\\documents\\github\\abot-master\\1.0\\libs\\cocos-headers\\extensions\\network\\httprequest.h",
            "c:\\users\\oli\\documents\\github\\abot-master\\1.0\\libs\\cocos-headers\\extensions\\network\\httpresponse.h",
            "c:\\users\\oli\\documents\\github\\abot-master\\1.0\\libs\\cocos-headers\\extensions\\network\\httpclient.h",
            "c:\\users\\oli\\documents\\github\\abot-master\\1.0\\libs\\gd.h\\include\\gdmacros.h",
            "c:\\users\\oli\\documents\\github\\abot-master\\1.0\\libs\\gd.h\\include\\gdprotocols.h",
            "c:\\users\\oli\\documents\\github\\abot-master\\1.0\\libs\\gd.h\\include\\gd.h",
            "c:\\users\\oli\\documents\\github\\abot-master\\1.0\\libs\\gd.h\\delegates\\delegates.h",
            "c:\\users\\oli\\documents\\github\\abot-master\\1.0\\libs\\gd.h\\actions\\cccirclewave.h",
            "c:\\users\\oli\\documents\\github\\abot-master\\1.0\\libs\\gd.h\\achievement_nodes\\achievementbar.h",
            "c:\\users\\oli\\documents\\github\\abot-master\\1.0\\libs\\gd.h\\achievement_nodes\\achievementnotifier.h",
            "c:\\users\\oli\\documents\\github\\abot-master\\1.0\\libs\\gd.h\\layers_scenes_transitions_nodes\\ccnodecontainer.h",
            "c:\\users\\oli\\documents\\github\\abot-master\\1.0\\libs\\gd.h\\layers_scenes_transitions_nodes\\obb2d.h",
            "c:\\users\\oli\\documents\\github\\abot-master\\1.0\\libs\\gd.h\\layers_scenes_transitions_nodes\\flalertlayer.h",
            "c:\\users\\oli\\documents\\github\\abot-master\\1.0\\libs\\gd.h\\layers_scenes_transitions_nodes\\gjdropdownlayer.h",
            "c:\\users\\oli\\documents\\github\\abot-master\\1.0\\libs\\gd.h\\layers_scenes_transitions_nodes\\gjlistlayer.h",
            "c:\\users\\oli\\documents\\github\\abot-master\\1.0\\libs\\gd.h\\layers_scenes_transitions_nodes\\loadinglayer.h",
            "c:\\users\\oli\\documents\\github\\abot-master\\1.0\\libs\\gd.h\\layers_scenes_transitions_nodes\\menulayer.h",
            "c:\\users\\oli\\documents\\github\\abot-master\\1.0\\libs\\gd.h\\layers_scenes_transitions_nodes\\textalertpopup.h",
            "c:\\users\\oli\\documents\\github\\abot-master\\1.0\\libs\\gd.h\\layers_scenes_transitions_nodes\\loadingcircle.h",
            "c:\\users\\oli\\documents\\github\\abot-master\\1.0\\libs\\gd.h\\layers_scenes_transitions_nodes\\ccblocklayer.h",
            "c:\\users\\oli\\documents\\github\\abot-master\\1.0\\libs\\gd.h\\layers_scenes_transitions_nodes\\pauselayer.h",
            "c:\\users\\oli\\documents\\github\\abot-master\\1.0\\libs\\gd.h\\layers_scenes_transitions_nodes\\gjbasegamelayer.h",
            "c:\\users\\oli\\documents\\github\\abot-master\\1.0\\libs\\gd.h\\layers_scenes_transitions_nodes\\playlayer.h",
            "c:\\users\\oli\\documents\\github\\abot-master\\1.0\\libs\\gd.h\\layers_scenes_transitions_nodes\\leveleditorlayer.h",
            "c:\\users\\oli\\documents\\github\\abot-master\\1.0\\libs\\gd.h\\layers_scenes_transitions_nodes\\editorui.h",
            "c:\\users\\oli\\documents\\github\\abot-master\\1.0\\libs\\gd.h\\layers_scenes_transitions_nodes\\numberinputlayer.h",
            "c:\\users\\oli\\documents\\github\\abot-master\\1.0\\libs\\gd.h\\layers_scenes_transitions_nodes\\setidpopup.h",
            "c:\\users\\oli\\documents\\github\\abot-master\\1.0\\libs\\gd.h\\layers_scenes_transitions_nodes\\customsongwidget.h",
            "c:\\users\\oli\\documents\\github\\abot-master\\1.0\\libs\\gd.h\\layers_scenes_transitions_nodes\\customsonglayer.h",
            "c:\\users\\oli\\documents\\github\\abot-master\\1.0\\libs\\gd.h\\layers_scenes_transitions_nodes\\songinfolayer.h",
            "c:\\users\\oli\\documents\\github\\abot-master\\1.0\\libs\\gd.h\\layers_scenes_transitions_nodes\\gjspecialcolorselect.h",
            "c:\\users\\oli\\documents\\github\\abot-master\\1.0\\libs\\gd.h\\layers_scenes_transitions_nodes\\setuppulsepopup.h",
            "c:\\users\\oli\\documents\\github\\abot-master\\1.0\\libs\\gd.h\\layers_scenes_transitions_nodes\\colorselectpopup.h",
            "c:\\users\\oli\\documents\\github\\abot-master\\1.0\\libs\\gd.h\\layers_scenes_transitions_nodes\\moreoptionslayer.h",
            "c:\\users\\oli\\documents\\github\\abot-master\\1.0\\libs\\gd.h\\scroll_nodes\\cccontentlayer.h",
            "c:\\users\\oli\\documents\\github\\abot-master\\1.0\\libs\\gd.h\\scroll_nodes\\ccindexpath.h",
            "c:\\users\\oli\\documents\\github\\abot-master\\1.0\\libs\\gd.h\\scroll_nodes\\ccscrolllayerext.h",
            "c:\\users\\oli\\documents\\github\\abot-master\\1.0\\libs\\gd.h\\scroll_nodes\\tableview.h",
            "c:\\users\\oli\\documents\\github\\abot-master\\1.0\\libs\\gd.h\\scroll_nodes\\boomlistview.h",
            "c:\\users\\oli\\documents\\github\\abot-master\\1.0\\libs\\gd.h\\scroll_nodes\\customlistview.h",
            "c:\\users\\oli\\documents\\github\\abot-master\\1.0\\libs\\gd.h\\scroll_nodes\\scrollinglayer.h",
            "c:\\users\\oli\\documents\\github\\abot-master\\1.0\\libs\\gd.h\\manager_nodes\\gmanager.h",
            "c:\\users\\oli\\documents\\github\\abot-master\\1.0\\libs\\gd.h\\manager_nodes\\gamemanager.h",
            "c:\\users\\oli\\documents\\github\\abot-master\\1.0\\libs\\gd.h\\manager_nodes\\gamesoundmanager.h",
            "c:\\program files\\microsoft visual studio\\2022\\community\\vc\\tools\\msvc\\14.43.34808\\include\\filesystem",
            "c:\\program files\\microsoft visual studio\\2022\\community\\vc\\tools\\msvc\\14.43.34808\\include\\algorithm",
            "c:\\program files\\microsoft visual studio\\2022\\community\\vc\\tools\\msvc\\14.43.34808\\include\\__msvc_heap_algorithms.hpp",
            "c:\\program files\\microsoft visual studio\\2022\\community\\vc\\tools\\msvc\\14.43.34808\\include\\__msvc_minmax.hpp",
            "c:\\program files\\microsoft visual studio\\2022\\community\\vc\\tools\\msvc\\14.43.34808\\include\\chrono",
            "c:\\program files\\microsoft visual studio\\2022\\community\\vc\\tools\\msvc\\14.43.34808\\include\\__msvc_chrono.hpp",
            "c:\\program files\\microsoft visual studio\\2022\\community\\vc\\tools\\msvc\\14.43.34808\\include\\ratio",
            "c:\\program files\\microsoft visual studio\\2022\\community\\vc\\tools\\msvc\\14.43.34808\\include\\__msvc_tzdb.hpp",
            "c:\\program files\\microsoft visual studio\\2022\\community\\vc\\tools\\msvc\\14.43.34808\\include\\forward_list",
            "c:\\program files\\microsoft visual studio\\2022\\community\\vc\\tools\\msvc\\14.43.34808\\include\\iomanip",
            "c:\\program files\\microsoft visual studio\\2022\\community\\vc\\tools\\msvc\\14.43.34808\\include\\optional",
            "c:\\program files\\microsoft visual studio\\2022\\community\\vc\\tools\\msvc\\14.43.34808\\include\\xsmf_control.h",
            "c:\\users\\oli\\documents\\github\\abot-master\\1.0\\libs\\gd.h\\manager_nodes\\gamelevelmanager.h",
            "c:\\users\\oli\\documents\\github\\abot-master\\1.0\\libs\\gd.h\\manager_nodes\\locallevelmanager.h",
            "c:\\users\\oli\\documents\\github\\abot-master\\1.0\\libs\\gd.h\\manager_nodes\\achievementmanager.h",
            "c:\\users\\oli\\documents\\github\\abot-master\\1.0\\libs\\gd.h\\manager_nodes\\gjuserscore.h",
            "c:\\users\\oli\\documents\\github\\abot-master\\1.0\\libs\\gd.h\\manager_nodes\\gjaccountmanager.h",
            "c:\\users\\oli\\documents\\github\\abot-master\\1.0\\libs\\gd.h\\manager_nodes\\gjeffectmanager.h",
            "c:\\users\\oli\\documents\\github\\abot-master\\1.0\\libs\\gd.h\\manager_nodes\\musicdownloadmanager.h",
            "c:\\users\\oli\\documents\\github\\abot-master\\1.0\\libs\\gd.h\\manager_nodes\\objecttoolbox.h",
            "c:\\users\\oli\\documents\\github\\abot-master\\1.0\\libs\\gd.h\\menu_nodes\\ccmenuitemspriteextra.h",
            "c:\\users\\oli\\documents\\github\\abot-master\\1.0\\libs\\gd.h\\menu_nodes\\ccmenuitemtoggler.h",
            "c:\\users\\oli\\documents\\github\\abot-master\\1.0\\libs\\gd.h\\menu_nodes\\slider.h",
            "c:\\users\\oli\\documents\\github\\abot-master\\1.0\\libs\\gd.h\\audio_nodes\\fmodaudioengine.h",
            "c:\\users\\oli\\documents\\github\\abot-master\\1.0\\libs\\gd.h\\audio_nodes\\fmodsound.h",
            "c:\\users\\oli\\documents\\github\\abot-master\\1.0\\libs\\gd.h\\level_nodes\\gjgamelevel.h",
            "c:\\users\\oli\\documents\\github\\abot-master\\1.0\\libs\\gd.h\\level_nodes\\gjsearchobject.h",
            "c:\\users\\oli\\documents\\github\\abot-master\\1.0\\libs\\gd.h\\level_nodes\\levelsettingsobject.h",
            "c:\\users\\oli\\documents\\github\\abot-master\\1.0\\libs\\gd.h\\level_nodes\\songinfoobject.h",
            "c:\\users\\oli\\documents\\github\\abot-master\\1.0\\libs\\gd.h\\level_nodes\\coloraction.h",
            "c:\\users\\oli\\documents\\github\\abot-master\\1.0\\libs\\gd.h\\sprite_nodes\\ccspriteplus.h",
            "c:\\users\\oli\\documents\\github\\abot-master\\1.0\\libs\\gd.h\\sprite_nodes\\coloractionsprite.h",
            "c:\\users\\oli\\documents\\github\\abot-master\\1.0\\libs\\gd.h\\sprite_nodes\\buttonsprite.h",
            "c:\\users\\oli\\documents\\github\\abot-master\\1.0\\libs\\gd.h\\sprite_nodes\\gameobject.h",
            "c:\\users\\oli\\documents\\github\\abot-master\\1.0\\libs\\gd.h\\sprite_nodes\\ccanimatedsprite.h",
            "c:\\users\\oli\\documents\\github\\abot-master\\1.0\\libs\\gd.h\\sprite_nodes\\animatedshopkeeper.h",
            "c:\\users\\oli\\documents\\github\\abot-master\\1.0\\libs\\gd.h\\sprite_nodes\\playerobject.h",
            "c:\\users\\oli\\documents\\github\\abot-master\\1.0\\libs\\gd.h\\sprite_nodes\\textarea.h",
            "c:\\users\\oli\\documents\\github\\abot-master\\1.0\\libs\\gd.h\\sprite_nodes\\gjitemicon.h",
            "c:\\users\\oli\\documents\\github\\abot-master\\1.0\\libs\\gd.h\\sprite_nodes\\gjrobotsprite.h",
            "c:\\users\\oli\\documents\\github\\abot-master\\1.0\\libs\\gd.h\\sprite_nodes\\gjspidersprite.h",
            "c:\\users\\oli\\documents\\github\\abot-master\\1.0\\libs\\gd.h\\sprite_nodes\\gjspritecolor.h",
            "c:\\users\\oli\\documents\\github\\abot-master\\1.0\\libs\\gd.h\\sprite_nodes\\simpleplayer.h",
            "c:\\users\\oli\\documents\\github\\abot-master\\1.0\\libs\\gd.h\\sprite_nodes\\hardstreak.h",
            "c:\\users\\oli\\documents\\github\\abot-master\\1.0\\libs\\gd.h\\sprite_nodes\\teleportportalobject.h",
            "c:\\users\\oli\\documents\\github\\abot-master\\1.0\\libs\\gd.h\\text_input_nodes\\cctextinputnode.h",
            "c:\\users\\oli\\documents\\github\\abot-master\\1.0\\libs\\gd.h\\other_nodes\\checkpointobject.h",
            "c:\\users\\oli\\documents\\github\\abot-master\\1.0\\libs\\gd.h\\other_nodes\\playercheckpoint.h",
            "c:\\users\\oli\\documents\\github\\abot-master\\1.0\\libs\\gd.h\\other_nodes\\pointnode.h",
            "c:\\users\\oli\\documents\\github\\abot-master\\1.0\\src\\console.h",
            "c:\\users\\oli\\documents\\github\\abot-master\\1.0\\src\\fpsbypass.h",
            "c:\\users\\oli\\documents\\github\\abot-master\\1.0\\libs\\minhook\\include\\minhook.h",
            "c:\\users\\oli\\documents\\github\\abot-master\\1.0\\src\\playlayer.h",
            "c:\\users\\oli\\documents\\github\\abot-master\\1.0\\src\\fpsbypass.h",
            "c:\\users\\oli\\documents\\github\\abot-master\\1.0\\src\\uselessshit.h",
            "c:\\users\\oli\\documents\\github\\abot-master\\1.0\\libs\\imgui-hook\\imgui\\imgui.h",
            "c:\\users\\oli\\documents\\github\\abot-master\\1.0\\libs\\imgui-hook\\imgui\\imconfig.h",
            "c:\\program files (x86)\\windows kits\\10\\include\\10.0.22621.0\\ucrt\\assert.h",
            "c:\\users\\oli\\documents\\github\\abot-master\\1.0\\src\\spambot.h",
            "c:\\users\\oli\\documents\\github\\abot-master\\1.0\\src\\console.h",
            "c:\\program files\\microsoft visual studio\\2022\\community\\vc\\tools\\msvc\\14.43.34808\\include\\thread",
            "c:\\program files (x86)\\windows kits\\10\\include\\10.0.22621.0\\ucrt\\process.h",
            "c:\\program files (x86)\\windows kits\\10\\include\\10.0.22621.0\\ucrt\\corecrt_startup.h",
            "c:\\program files (x86)\\windows kits\\10\\include\\10.0.22621.0\\ucrt\\math.h",
            "c:\\program files\\microsoft visual studio\\2022\\community\\vc\\tools\\msvc\\14.43.34808\\include\\vcruntime_startup.h",
            "c:\\program files\\microsoft visual studio\\2022\\community\\vc\\tools\\msvc\\14.43.34808\\include\\stop_token",
            "c:\\users\\oli\\documents\\github\\abot-master\\1.0\\src\\spambot.h",
            "c:\\users\\oli\\documents\\github\\abot-master\\1.0\\libs\\imgui-hook\\imgui_hook.h",
            "c:\\users\\oli\\documents\\github\\abot-master\\1.0\\libs\\imgui-hook\\imgui\\imgui_internal.h",
            "c:\\program files (x86)\\windows kits\\10\\include\\10.0.22621.0\\ucrt\\math.h",
            "c:\\users\\oli\\documents\\github\\abot-master\\1.0\\libs\\imgui-hook\\imgui\\imstb_textedit.h",
            "c:\\users\\oli\\documents\\github\\abot-master\\1.0\\src\\hwid.h"
        ],
        "ImportedModules": [],
        "ImportedHeaderUnits": []
    }
}